LICENSE
MANIFEST.in
README.rst
randfilter.py
requirements.txt
setup.py
randfilter.egg-info/PKG-INFO
randfilter.egg-info/SOURCES.txt
randfilter.egg-info/dependency_links.txt
randfilter.egg-info/entry_points.txt
randfilter.egg-info/requires.txt
randfilter.egg-info/top_level.txt