Metadata-Version: 1.1
Name: randfilter
Version: 1.0.0
Summary: This tool reads files or stdin and outputs random lines.
Home-page: https://github.com/ton1517/randfilter
Author: ton1517
Author-email: tonton1517@gmail.com
License: MIT License
Platform: UNKNOWN
Classifier: Development Status :: 3 - Alpha
Classifier: Environment :: Console
Classifier: License :: OSI Approved :: MIT License
Classifier: Operating System :: MacOS :: MacOS X
Classifier: Operating System :: Unix
Classifier: Operating System :: POSIX :: Linux
Classifier: Programming Language :: Python :: 2.7
Classifier: Programming Language :: Python :: 3.3
Classifier: Topic :: Utilities
